[
  {
    "trend_arrow": "FLAT", 
    "display_time": "2017-02-18T00:32:43-08:00", 
    "noise": 1, 
    "system_time": "2017-02-18T08:31:52-08:00", 
    "direction": "Flat", 
    "sgv": 63, 
    "dateString": "2017-02-18T00:32:43-08:00", 
    "date": 1487406763000, 
    "unfiltered": 82688, 
    "filtered": 86032, 
    "device": "openaps://indy-e1/cgm", 
    "rssi": 185, 
    "type": "sgv", 
    "glucose": 63
  }, 
  {
    "trend_arrow": "FLAT", 
    "display_time": "2017-02-18T00:27:43-08:00", 
    "noise": 1, 
    "system_time": "2017-02-18T08:26:52-08:00", 
    "direction": "Flat", 
    "sgv": 66, 
    "dateString": "2017-02-18T00:27:43-08:00", 
    "date": 1487406463000, 
    "unfiltered": 85360, 
    "filtered": 88528, 
    "device": "openaps://indy-e1/cgm", 
    "rssi": 193, 
    "type": "sgv", 
    "glucose": 66
  }
]