[
  {
    "trend_arrow": "FLAT", 
    "display_time": "2017-02-12T23:37:58-08:00", 
    "noise": 1, 
    "system_time": "2017-02-13T07:37:07-08:00", 
    "direction": "Flat", 
    "sgv": 246, 
    "dateString": "2017-02-12T23:37:58-08:00", 
    "date": 1486971478000, 
    "unfiltered": 288256, 
    "filtered": 283904, 
    "device": "openaps://indy-e1/cgm", 
    "rssi": 184, 
    "type": "sgv", 
    "glucose": 246
  }, 
  {
    "trend_arrow": "FLAT", 
    "display_time": "2017-02-12T23:32:58-08:00", 
    "noise": 1, 
    "system_time": "2017-02-13T07:32:07-08:00", 
    "direction": "Flat", 
    "sgv": 244, 
    "dateString": "2017-02-12T23:32:58-08:00", 
    "date": 1486971178000, 
    "unfiltered": 286272, 
    "filtered": 280192, 
    "device": "openaps://indy-e1/cgm", 
    "rssi": 186, 
    "type": "sgv", 
    "glucose": 244
  }
]