[
  {
    "trend_arrow": "FLAT", 
    "display_time": "2017-02-19T09:02:39-08:00", 
    "noise": 1, 
    "system_time": "2017-02-19T17:01:48-08:00", 
    "direction": "Flat", 
    "sgv": 86, 
    "dateString": "2017-02-19T09:02:39-08:00", 
    "date": 1487523759000, 
    "unfiltered": 96096, 
    "filtered": 100192, 
    "device": "openaps://indy-e1/cgm", 
    "rssi": 183, 
    "type": "sgv", 
    "glucose": 86
  }, 
  {
    "trend_arrow": "FLAT", 
    "display_time": "2017-02-19T08:57:39-08:00", 
    "noise": 1, 
    "system_time": "2017-02-19T16:56:48-08:00", 
    "direction": "Flat", 
    "sgv": 88, 
    "dateString": "2017-02-19T08:57:39-08:00", 
    "date": 1487523459000, 
    "unfiltered": 97664, 
    "filtered": 103888, 
    "device": "openaps://indy-e1/cgm", 
    "rssi": 189, 
    "type": "sgv", 
    "glucose": 88
  }
]