[
  {
    "trend_arrow": "FLAT", 
    "display_time": "2017-02-02T05:52:32-08:00", 
    "noise": 1, 
    "system_time": "2017-02-02T13:51:45-08:00", 
    "direction": "Flat", 
    "sgv": 90, 
    "dateString": "2017-02-02T05:52:32-08:00", 
    "date": 1486043552000, 
    "unfiltered": 102128, 
    "filtered": 105392, 
    "device": "openaps://indy-e1/cgm", 
    "rssi": 185, 
    "type": "sgv", 
    "glucose": 90
  }, 
  {
    "trend_arrow": "FLAT", 
    "display_time": "2017-02-02T05:47:32-08:00", 
    "noise": 1, 
    "system_time": "2017-02-02T13:46:45-08:00", 
    "direction": "Flat", 
    "sgv": 93, 
    "dateString": "2017-02-02T05:47:32-08:00", 
    "date": 1486043252000, 
    "unfiltered": 104336, 
    "filtered": 106064, 
    "device": "openaps://indy-e1/cgm", 
    "rssi": 186, 
    "type": "sgv", 
    "glucose": 93
  }
]