[
  {
    "trend_arrow": "FLAT", 
    "display_time": "2017-02-09T01:03:04-08:00", 
    "noise": 1, 
    "system_time": "2017-02-09T08:48:18-08:00", 
    "direction": "Flat", 
    "sgv": 93, 
    "dateString": "2017-02-09T01:03:04-08:00", 
    "date": 1486630984000, 
    "unfiltered": 107792, 
    "filtered": 108000, 
    "device": "openaps://indy-e1/cgm", 
    "rssi": 196, 
    "type": "sgv", 
    "glucose": 93
  }, 
  {
    "trend_arrow": "FLAT", 
    "display_time": "2017-02-09T00:58:05-08:00", 
    "noise": 1, 
    "system_time": "2017-02-09T08:43:18-08:00", 
    "direction": "Flat", 
    "sgv": 93, 
    "dateString": "2017-02-09T00:58:05-08:00", 
    "date": 1486630685000, 
    "unfiltered": 108224, 
    "filtered": 107840, 
    "device": "openaps://indy-e1/cgm", 
    "rssi": 447, 
    "type": "sgv", 
    "glucose": 93
  }
]