[
  {
    "trend_arrow": "FLAT", 
    "display_time": "2017-02-02T02:32:32-08:00", 
    "noise": 1, 
    "system_time": "2017-02-02T10:31:45-08:00", 
    "direction": "Flat", 
    "sgv": 83, 
    "dateString": "2017-02-02T02:32:32-08:00", 
    "date": 1486031552000, 
    "unfiltered": 96464, 
    "filtered": 100304, 
    "device": "openaps://indy-e1/cgm", 
    "rssi": 175, 
    "type": "sgv", 
    "glucose": 83
  }, 
  {
    "trend_arrow": "FLAT", 
    "display_time": "2017-02-02T02:27:32-08:00", 
    "noise": 1, 
    "system_time": "2017-02-02T10:26:45-08:00", 
    "direction": "Flat", 
    "sgv": 87, 
    "dateString": "2017-02-02T02:27:32-08:00", 
    "date": 1486031252000, 
    "unfiltered": 99312, 
    "filtered": 101728, 
    "device": "openaps://indy-e1/cgm", 
    "rssi": 186, 
    "type": "sgv", 
    "glucose": 87
  }
]