[
  {
    "trend_arrow": "FLAT", 
    "display_time": "2017-02-13T02:32:58-08:00", 
    "noise": 1, 
    "system_time": "2017-02-13T10:32:07-08:00", 
    "direction": "Flat", 
    "sgv": 216, 
    "dateString": "2017-02-13T02:32:58-08:00", 
    "date": 1486981978000, 
    "unfiltered": 254240, 
    "filtered": 249824, 
    "device": "openaps://indy-e1/cgm", 
    "rssi": 190, 
    "type": "sgv", 
    "glucose": 216
  }, 
  {
    "trend_arrow": "FLAT", 
    "display_time": "2017-02-13T02:27:58-08:00", 
    "noise": 1, 
    "system_time": "2017-02-13T10:27:07-08:00", 
    "direction": "Flat", 
    "sgv": 214, 
    "dateString": "2017-02-13T02:27:58-08:00", 
    "date": 1486981678000, 
    "unfiltered": 252416, 
    "filtered": 247296, 
    "device": "openaps://indy-e1/cgm", 
    "rssi": 192, 
    "type": "sgv", 
    "glucose": 214
  }
]