[
  {
    "trend_arrow": "FLAT", 
    "display_time": "2017-02-14T18:17:53-08:00", 
    "noise": 1, 
    "system_time": "2017-02-15T02:17:02-08:00", 
    "direction": "Flat", 
    "sgv": 80, 
    "dateString": "2017-02-14T18:17:53-08:00", 
    "date": 1487125073000, 
    "unfiltered": 101488, 
    "filtered": 94112, 
    "device": "openaps://indy-e1/cgm", 
    "rssi": 198, 
    "type": "sgv", 
    "glucose": 80
  }, 
  {
    "trend_arrow": "FLAT", 
    "display_time": "2017-02-14T18:12:53-08:00", 
    "noise": 1, 
    "system_time": "2017-02-15T02:12:02-08:00", 
    "direction": "Flat", 
    "sgv": 75, 
    "dateString": "2017-02-14T18:12:53-08:00", 
    "date": 1487124773000, 
    "unfiltered": 96992, 
    "filtered": 94528, 
    "device": "openaps://indy-e1/cgm", 
    "rssi": 200, 
    "type": "sgv", 
    "glucose": 75
  }
]