[
  {
    "trend_arrow": "FLAT", 
    "display_time": "2017-02-11T01:47:55-08:00", 
    "noise": 1, 
    "system_time": "2017-02-11T09:33:09-08:00", 
    "direction": "Flat", 
    "sgv": 154, 
    "dateString": "2017-02-11T01:47:55-08:00", 
    "device": "openaps://indy-e1/cgm", 
    "unfiltered": 163008, 
    "rssi": 191, 
    "date": 1486806475000, 
    "filtered": 163808, 
    "type": "sgv", 
    "glucose": 154
  }, 
  {
    "trend_arrow": "FLAT", 
    "display_time": "2017-02-11T01:42:55-08:00", 
    "noise": 1, 
    "system_time": "2017-02-11T09:28:09-08:00", 
    "direction": "Flat", 
    "sgv": 154, 
    "dateString": "2017-02-11T01:42:55-08:00", 
    "device": "openaps://indy-e1/cgm", 
    "unfiltered": 163392, 
    "rssi": 189, 
    "date": 1486806175000, 
    "filtered": 163136, 
    "type": "sgv", 
    "glucose": 154
  }
]