[
  {
    "trend_arrow": "FLAT", 
    "system_time": "2017-02-19T18:46:48", 
    "noise": 1, 
    "direction": "Flat", 
    "sgv": 95, 
    "display_time": "2017-02-19T10:47:38", 
    "date": 1487530058000.0, 
    "dateString": "2017-02-19T10:47:38", 
    "unfiltered": 105584, 
    "filtered": 106032, 
    "device": "openaps://indy-e1/cgm", 
    "rssi": 192, 
    "type": "sgv", 
    "glucose": 95
  }, 
  {
    "trend_arrow": "FLAT", 
    "system_time": "2017-02-19T18:41:48", 
    "noise": 1, 
    "direction": "Flat", 
    "sgv": 95, 
    "display_time": "2017-02-19T10:42:38", 
    "date": 1487529758000.0, 
    "dateString": "2017-02-19T10:42:38", 
    "unfiltered": 106176, 
    "filtered": 104848, 
    "device": "openaps://indy-e1/cgm", 
    "rssi": 193, 
    "type": "sgv", 
    "glucose": 95
  }, 
  {
    "trend_arrow": "FLAT", 
    "system_time": "2017-02-19T18:36:48", 
    "noise": 1, 
    "direction": "Flat", 
    "sgv": 95, 
    "display_time": "2017-02-19T10:37:38", 
    "date": 1487529458000.0, 
    "dateString": "2017-02-19T10:37:38", 
    "unfiltered": 105840, 
    "filtered": 103056, 
    "device": "openaps://indy-e1/cgm", 
    "rssi": 191, 
    "type": "sgv", 
    "glucose": 95
  }, 
  {
    "trend_arrow": "FLAT", 
    "system_time": "2017-02-19T18:31:48", 
    "noise": 1, 
    "direction": "Flat", 
    "sgv": 94, 
    "display_time": "2017-02-19T10:32:39", 
    "date": 1487529159000.0, 
    "dateString": "2017-02-19T10:32:39", 
    "unfiltered": 104640, 
    "filtered": 101296, 
    "device": "openaps://indy-e1/cgm", 
    "rssi": 177, 
    "type": "sgv", 
    "glucose": 94
  }, 
  {
    "trend_arrow": "FLAT", 
    "system_time": "2017-02-19T18:26:48", 
    "noise": 1, 
    "direction": "Flat", 
    "sgv": 92, 
    "display_time": "2017-02-19T10:27:38", 
    "date": 1487528858000.0, 
    "dateString": "2017-02-19T10:27:38", 
    "unfiltered": 102752, 
    "filtered": 99600, 
    "device": "openaps://indy-e1/cgm", 
    "rssi": 196, 
    "type": "sgv", 
    "glucose": 92
  }, 
  {
    "trend_arrow": "FLAT", 
    "system_time": "2017-02-19T18:21:48", 
    "noise": 1, 
    "direction": "Flat", 
    "sgv": 87, 
    "display_time": "2017-02-19T10:22:39", 
    "date": 1487528559000.0, 
    "dateString": "2017-02-19T10:22:39", 
    "unfiltered": 98768, 
    "filtered": 97808, 
    "device": "openaps://indy-e1/cgm", 
    "rssi": 196, 
    "type": "sgv", 
    "glucose": 87
  }
]