[
  {
    "trend_arrow": "FLAT", 
    "system_time": "2017-02-13T07:22:08", 
    "noise": 1, 
    "direction": "Flat", 
    "sgv": 237, 
    "display_time": "2017-02-12T23:22:59", 
    "date": 1486970579000.0, 
    "dateString": "2017-02-12T23:22:59", 
    "unfiltered": 277888, 
    "filtered": 272192, 
    "device": "openaps://indy-e1/cgm", 
    "rssi": 440, 
    "type": "sgv", 
    "glucose": 237
  }, 
  {
    "trend_arrow": "FLAT", 
    "system_time": "2017-02-13T07:17:08", 
    "noise": 1, 
    "direction": "Flat", 
    "sgv": 234, 
    "display_time": "2017-02-12T23:17:59", 
    "date": 1486970279000.0, 
    "dateString": "2017-02-12T23:17:59", 
    "unfiltered": 274816, 
    "filtered": 268800, 
    "device": "openaps://indy-e1/cgm", 
    "rssi": 439, 
    "type": "sgv", 
    "glucose": 234
  }, 
  {
    "trend_arrow": "FLAT", 
    "system_time": "2017-02-13T07:12:08", 
    "noise": 1, 
    "direction": "Flat", 
    "sgv": 231, 
    "display_time": "2017-02-12T23:12:58", 
    "date": 1486969978000.0, 
    "dateString": "2017-02-12T23:12:58", 
    "unfiltered": 271104, 
    "filtered": 266240, 
    "device": "openaps://indy-e1/cgm", 
    "rssi": 187, 
    "type": "sgv", 
    "glucose": 231
  }, 
  {
    "trend_arrow": "FLAT", 
    "system_time": "2017-02-13T07:07:08", 
    "noise": 1, 
    "direction": "Flat", 
    "sgv": 227, 
    "display_time": "2017-02-12T23:07:58", 
    "date": 1486969678000.0, 
    "dateString": "2017-02-12T23:07:58", 
    "unfiltered": 267264, 
    "filtered": 264128, 
    "device": "openaps://indy-e1/cgm", 
    "rssi": 187, 
    "type": "sgv", 
    "glucose": 227
  }, 
  {
    "trend_arrow": "FLAT", 
    "system_time": "2017-02-13T07:02:08", 
    "noise": 1, 
    "direction": "Flat", 
    "sgv": 225, 
    "display_time": "2017-02-12T23:02:58", 
    "date": 1486969378000.0, 
    "dateString": "2017-02-12T23:02:58", 
    "unfiltered": 264448, 
    "filtered": 261696, 
    "device": "openaps://indy-e1/cgm", 
    "rssi": 187, 
    "type": "sgv", 
    "glucose": 225
  }, 
  {
    "trend_arrow": "FLAT", 
    "system_time": "2017-02-13T06:57:08", 
    "noise": 1, 
    "direction": "Flat", 
    "sgv": 223, 
    "display_time": "2017-02-12T22:57:58", 
    "date": 1486969078000.0, 
    "dateString": "2017-02-12T22:57:58", 
    "unfiltered": 262656, 
    "filtered": 258240, 
    "device": "openaps://indy-e1/cgm", 
    "rssi": 186, 
    "type": "sgv", 
    "glucose": 223
  }
]