[
  {
    "trend_arrow": "FLAT", 
    "system_time": "2017-02-14T07:52:05", 
    "noise": 1, 
    "direction": "Flat", 
    "sgv": 146, 
    "display_time": "2017-02-13T23:52:55", 
    "date": 1487058775000.0, 
    "dateString": "2017-02-13T23:52:55", 
    "unfiltered": 174624, 
    "filtered": 178560, 
    "device": "openaps://indy-e1/cgm", 
    "rssi": 436, 
    "type": "sgv", 
    "glucose": 146
  }, 
  {
    "trend_arrow": "FLAT", 
    "system_time": "2017-02-14T07:47:05", 
    "noise": 1, 
    "direction": "Flat", 
    "sgv": 149, 
    "display_time": "2017-02-13T23:47:55", 
    "date": 1487058475000.0, 
    "dateString": "2017-02-13T23:47:55", 
    "unfiltered": 178176, 
    "filtered": 180704, 
    "device": "openaps://indy-e1/cgm", 
    "rssi": 186, 
    "type": "sgv", 
    "glucose": 149
  }, 
  {
    "trend_arrow": "FLAT", 
    "system_time": "2017-02-14T07:42:04", 
    "noise": 1, 
    "direction": "Flat", 
    "sgv": 151, 
    "display_time": "2017-02-13T23:42:55", 
    "date": 1487058175000.0, 
    "dateString": "2017-02-13T23:42:55", 
    "unfiltered": 180704, 
    "filtered": 184160, 
    "device": "openaps://indy-e1/cgm", 
    "rssi": 185, 
    "type": "sgv", 
    "glucose": 151
  }, 
  {
    "trend_arrow": "FLAT", 
    "system_time": "2017-02-14T07:37:04", 
    "noise": 1, 
    "direction": "Flat", 
    "sgv": 153, 
    "display_time": "2017-02-13T23:37:55", 
    "date": 1487057875000.0, 
    "dateString": "2017-02-13T23:37:55", 
    "unfiltered": 182784, 
    "filtered": 189216, 
    "device": "openaps://indy-e1/cgm", 
    "rssi": 185, 
    "type": "sgv", 
    "glucose": 153
  }, 
  {
    "trend_arrow": "FLAT", 
    "system_time": "2017-02-14T07:32:05", 
    "noise": 1, 
    "direction": "Flat", 
    "sgv": 155, 
    "display_time": "2017-02-13T23:32:55", 
    "date": 1487057575000.0, 
    "dateString": "2017-02-13T23:32:55", 
    "unfiltered": 185056, 
    "filtered": 194400, 
    "device": "openaps://indy-e1/cgm", 
    "rssi": 185, 
    "type": "sgv", 
    "glucose": 155
  }, 
  {
    "trend_arrow": "FLAT", 
    "system_time": "2017-02-14T07:27:04", 
    "noise": 1, 
    "direction": "Flat", 
    "sgv": 159, 
    "display_time": "2017-02-13T23:27:55", 
    "date": 1487057275000.0, 
    "dateString": "2017-02-13T23:27:55", 
    "unfiltered": 189600, 
    "filtered": 197984, 
    "device": "openaps://indy-e1/cgm", 
    "rssi": 182, 
    "type": "sgv", 
    "glucose": 159
  }
]