[
  {
    "trend_arrow": "45_UP", 
    "display_time": "2017-02-10T13:02:58-08:00", 
    "noise": 1, 
    "system_time": "2017-02-10T20:48:11-08:00", 
    "direction": "FortyFiveUp", 
    "sgv": 114, 
    "dateString": "2017-02-10T13:02:58-08:00", 
    "device": "openaps://indy-e1/cgm", 
    "unfiltered": 126672, 
    "rssi": 191, 
    "date": 1486760578000, 
    "filtered": 112880, 
    "type": "sgv", 
    "glucose": 114
  }, 
  {
    "trend_arrow": "FLAT", 
    "display_time": "2017-02-10T12:57:58-08:00", 
    "noise": 1, 
    "system_time": "2017-02-10T20:43:12-08:00", 
    "direction": "Flat", 
    "sgv": 103, 
    "dateString": "2017-02-10T12:57:58-08:00", 
    "device": "openaps://indy-e1/cgm", 
    "unfiltered": 116656, 
    "rssi": 433, 
    "date": 1486760278000, 
    "filtered": 108656, 
    "type": "sgv", 
    "glucose": 103
  }
]