[
  {
    "trend_arrow": "45_DOWN", 
    "display_time": "2017-02-18T23:02:40-08:00", 
    "noise": 2, 
    "system_time": "2017-02-19T07:01:49-08:00", 
    "direction": "FortyFiveDown", 
    "sgv": 132, 
    "dateString": "2017-02-18T23:02:40-08:00", 
    "device": "openaps://indy-e1/cgm", 
    "unfiltered": 163520, 
    "rssi": 185, 
    "date": 1487487760000, 
    "filtered": 148320, 
    "type": "sgv", 
    "glucose": 132
  }, 
  {
    "trend_arrow": "SINGLE_DOWN", 
    "display_time": "2017-02-18T22:57:40-08:00", 
    "noise": 2, 
    "system_time": "2017-02-19T06:56:50-08:00", 
    "direction": "SingleDown", 
    "sgv": 133, 
    "dateString": "2017-02-18T22:57:40-08:00", 
    "device": "openaps://indy-e1/cgm", 
    "unfiltered": 154208, 
    "rssi": 449, 
    "date": 1487487460000, 
    "filtered": 149184, 
    "type": "sgv", 
    "glucose": 133
  }
]