[
  {
    "trend_arrow": "FLAT", 
    "display_time": "2017-02-11T14:22:54-08:00", 
    "noise": 1, 
    "system_time": "2017-02-11T22:08:07-08:00", 
    "direction": "Flat", 
    "sgv": 165, 
    "dateString": "2017-02-11T14:22:54-08:00", 
    "device": "openaps://indy-e1/cgm", 
    "unfiltered": 173280, 
    "rssi": 429, 
    "date": 1486851774000, 
    "filtered": 170816, 
    "type": "sgv", 
    "glucose": 165
  }, 
  {
    "trend_arrow": "45_UP", 
    "display_time": "2017-02-11T14:17:54-08:00", 
    "noise": 1, 
    "system_time": "2017-02-11T22:03:07-08:00", 
    "direction": "FortyFiveUp", 
    "sgv": 163, 
    "dateString": "2017-02-11T14:17:54-08:00", 
    "device": "openaps://indy-e1/cgm", 
    "unfiltered": 171776, 
    "rssi": 428, 
    "date": 1486851474000, 
    "filtered": 162720, 
    "type": "sgv", 
    "glucose": 163
  }
]