[
  {
    "trend_arrow": "DOUBLE_UP", 
    "display_time": "2017-02-09T10:43:03-08:00", 
    "noise": 1, 
    "system_time": "2017-02-09T18:28:16-08:00", 
    "direction": "DoubleUp", 
    "sgv": 144, 
    "dateString": "2017-02-09T10:43:03-08:00", 
    "device": "openaps://indy-e1/cgm", 
    "unfiltered": 152960, 
    "rssi": 190, 
    "date": 1486665783000, 
    "filtered": 130592, 
    "type": "sgv", 
    "glucose": 144
  }, 
  {
    "trend_arrow": "DOUBLE_UP", 
    "display_time": "2017-02-09T10:38:03-08:00", 
    "noise": 1, 
    "system_time": "2017-02-09T18:23:16-08:00", 
    "direction": "DoubleUp", 
    "sgv": 129, 
    "dateString": "2017-02-09T10:38:03-08:00", 
    "device": "openaps://indy-e1/cgm", 
    "unfiltered": 139456, 
    "rssi": 181, 
    "date": 1486665483000, 
    "filtered": 114992, 
    "type": "sgv", 
    "glucose": 129
  }
]