[
  {
    "trend_arrow": "FLAT", 
    "system_time": "2017-02-15T21:02:00", 
    "noise": 1, 
    "direction": "Flat", 
    "sgv": 64, 
    "display_time": "2017-02-15T13:02:50", 
    "date": 1487192570000.0, 
    "dateString": "2017-02-15T13:02:50", 
    "unfiltered": 86560, 
    "filtered": 85728, 
    "device": "openaps://indy-e1/cgm", 
    "rssi": 193, 
    "type": "sgv", 
    "glucose": 64
  }, 
  {
    "trend_arrow": "45_DOWN", 
    "system_time": "2017-02-15T20:57:00", 
    "noise": 1, 
    "direction": "FortyFiveDown", 
    "sgv": 61, 
    "display_time": "2017-02-15T12:57:50", 
    "date": 1487192270000.0, 
    "dateString": "2017-02-15T12:57:50", 
    "unfiltered": 84272, 
    "filtered": 90384, 
    "device": "openaps://indy-e1/cgm", 
    "rssi": 193, 
    "type": "sgv", 
    "glucose": 61
  }, 
  {
    "trend_arrow": "45_DOWN", 
    "system_time": "2017-02-15T20:52:00", 
    "noise": 1, 
    "direction": "FortyFiveDown", 
    "sgv": 63, 
    "display_time": "2017-02-15T12:52:50", 
    "date": 1487191970000.0, 
    "dateString": "2017-02-15T12:52:50", 
    "unfiltered": 85952, 
    "filtered": 96512, 
    "device": "openaps://indy-e1/cgm", 
    "rssi": 200, 
    "type": "sgv", 
    "glucose": 63
  }, 
  {
    "trend_arrow": "45_DOWN", 
    "system_time": "2017-02-15T20:47:00", 
    "noise": 1, 
    "direction": "FortyFiveDown", 
    "sgv": 70, 
    "display_time": "2017-02-15T12:47:51", 
    "date": 1487191671000.0, 
    "dateString": "2017-02-15T12:47:51", 
    "unfiltered": 92032, 
    "filtered": 102128, 
    "device": "openaps://indy-e1/cgm", 
    "rssi": 427, 
    "type": "sgv", 
    "glucose": 70
  }, 
  {
    "trend_arrow": "FLAT", 
    "system_time": "2017-02-15T20:42:00", 
    "noise": 1, 
    "direction": "Flat", 
    "sgv": 79, 
    "display_time": "2017-02-15T12:42:50", 
    "date": 1487191370000.0, 
    "dateString": "2017-02-15T12:42:50", 
    "unfiltered": 99344, 
    "filtered": 106480, 
    "device": "openaps://indy-e1/cgm", 
    "rssi": 196, 
    "type": "sgv", 
    "glucose": 79
  }, 
  {
    "trend_arrow": "FLAT", 
    "system_time": "2017-02-15T20:37:00", 
    "noise": 1, 
    "direction": "Flat", 
    "sgv": 86, 
    "display_time": "2017-02-15T12:37:50", 
    "date": 1487191070000.0, 
    "dateString": "2017-02-15T12:37:50", 
    "unfiltered": 105408, 
    "filtered": 109744, 
    "device": "openaps://indy-e1/cgm", 
    "rssi": 197, 
    "type": "sgv", 
    "glucose": 86
  }
]