[
  {
    "trend_arrow": "FLAT", 
    "system_time": "2017-02-16T13:26:58", 
    "noise": 1, 
    "direction": "Flat", 
    "sgv": 111, 
    "display_time": "2017-02-16T05:27:48", 
    "date": 1487251668000.0, 
    "dateString": "2017-02-16T05:27:48", 
    "unfiltered": 126256, 
    "filtered": 131296, 
    "device": "openaps://indy-e1/cgm", 
    "rssi": 180, 
    "type": "sgv", 
    "glucose": 111
  }, 
  {
    "trend_arrow": "FLAT", 
    "system_time": "2017-02-16T13:21:58", 
    "noise": 1, 
    "direction": "Flat", 
    "sgv": 114, 
    "display_time": "2017-02-16T05:22:48", 
    "date": 1487251368000.0, 
    "dateString": "2017-02-16T05:22:48", 
    "unfiltered": 128656, 
    "filtered": 133856, 
    "device": "openaps://indy-e1/cgm", 
    "rssi": 185, 
    "type": "sgv", 
    "glucose": 114
  }, 
  {
    "trend_arrow": "FLAT", 
    "system_time": "2017-02-16T13:16:58", 
    "noise": 1, 
    "direction": "Flat", 
    "sgv": 117, 
    "display_time": "2017-02-16T05:17:48", 
    "date": 1487251068000.0, 
    "dateString": "2017-02-16T05:17:48", 
    "unfiltered": 132000, 
    "filtered": 134816, 
    "device": "openaps://indy-e1/cgm", 
    "rssi": 185, 
    "type": "sgv", 
    "glucose": 117
  }, 
  {
    "trend_arrow": "FLAT", 
    "system_time": "2017-02-16T13:11:58", 
    "noise": 1, 
    "direction": "Flat", 
    "sgv": 121, 
    "display_time": "2017-02-16T05:12:48", 
    "date": 1487250768000.0, 
    "dateString": "2017-02-16T05:12:48", 
    "unfiltered": 134688, 
    "filtered": 134240, 
    "device": "openaps://indy-e1/cgm", 
    "rssi": 186, 
    "type": "sgv", 
    "glucose": 121
  }, 
  {
    "trend_arrow": "FLAT", 
    "system_time": "2017-02-16T13:06:58", 
    "noise": 1, 
    "direction": "Flat", 
    "sgv": 122, 
    "display_time": "2017-02-16T05:07:48", 
    "date": 1487250468000.0, 
    "dateString": "2017-02-16T05:07:48", 
    "unfiltered": 135936, 
    "filtered": 132960, 
    "device": "openaps://indy-e1/cgm", 
    "rssi": 195, 
    "type": "sgv", 
    "glucose": 122
  }, 
  {
    "trend_arrow": "FLAT", 
    "system_time": "2017-02-16T13:01:58", 
    "noise": 1, 
    "direction": "Flat", 
    "sgv": 119, 
    "display_time": "2017-02-16T05:02:48", 
    "date": 1487250168000.0, 
    "dateString": "2017-02-16T05:02:48", 
    "unfiltered": 133664, 
    "filtered": 131712, 
    "device": "openaps://indy-e1/cgm", 
    "rssi": 192, 
    "type": "sgv", 
    "glucose": 119
  }
]