[
  {
    "trend_arrow": "45_DOWN", 
    "display_time": "2017-02-15T02:27:52-08:00", 
    "noise": 1, 
    "system_time": "2017-02-15T10:27:01-08:00", 
    "direction": "FortyFiveDown", 
    "sgv": 166, 
    "dateString": "2017-02-15T02:27:52-08:00", 
    "device": "openaps://indy-e1/cgm", 
    "unfiltered": 172128, 
    "rssi": 197, 
    "date": 1487154472000, 
    "filtered": 188512, 
    "type": "sgv", 
    "glucose": 166
  }, 
  {
    "trend_arrow": "45_DOWN", 
    "display_time": "2017-02-15T02:22:52-08:00", 
    "noise": 1, 
    "system_time": "2017-02-15T10:22:01-08:00", 
    "direction": "FortyFiveDown", 
    "sgv": 179, 
    "dateString": "2017-02-15T02:22:52-08:00", 
    "device": "openaps://indy-e1/cgm", 
    "unfiltered": 183616, 
    "rssi": 198, 
    "date": 1487154172000, 
    "filtered": 194368, 
    "type": "sgv", 
    "glucose": 179
  }
]