[
  {
    "trend_arrow": "45_DOWN", 
    "display_time": "2017-02-02T18:42:30-08:00", 
    "noise": 1, 
    "direction": "FortyFiveDown", 
    "system_time": "2017-02-03T02:41:43-08:00", 
    "sgv": 84, 
    "dateString": "2017-02-02T18:42:30-08:00", 
    "device": "openaps://indy-e1/cgm", 
    "unfiltered": 96480, 
    "rssi": 191, 
    "date": 1486089750000.0, 
    "filtered": 109696, 
    "type": "sgv", 
    "glucose": 84
  }, 
  {
    "trend_arrow": "45_DOWN", 
    "display_time": "2017-02-02T18:37:30-08:00", 
    "noise": 1, 
    "direction": "FortyFiveDown", 
    "system_time": "2017-02-03T02:36:43-08:00", 
    "sgv": 96, 
    "dateString": "2017-02-02T18:37:30-08:00", 
    "device": "openaps://indy-e1/cgm", 
    "unfiltered": 106880, 
    "rssi": 189, 
    "date": 1486089450000.0, 
    "filtered": 116656, 
    "type": "sgv", 
    "glucose": 96
  }, 
  {
    "trend_arrow": "45_DOWN", 
    "display_time": "2017-02-02T18:32:30-08:00", 
    "noise": 1, 
    "direction": "FortyFiveDown", 
    "system_time": "2017-02-03T02:31:43-08:00", 
    "sgv": 104, 
    "dateString": "2017-02-02T18:32:30-08:00", 
    "device": "openaps://indy-e1/cgm", 
    "unfiltered": 113600, 
    "rssi": 176, 
    "date": 1486089150000.0, 
    "filtered": 123360, 
    "type": "sgv", 
    "glucose": 104
  }, 
  {
    "trend_arrow": "45_DOWN", 
    "display_time": "2017-02-02T18:27:31-08:00", 
    "noise": 1, 
    "direction": "FortyFiveDown", 
    "system_time": "2017-02-03T02:26:43-08:00", 
    "sgv": 111, 
    "dateString": "2017-02-02T18:27:31-08:00", 
    "device": "openaps://indy-e1/cgm", 
    "unfiltered": 119040, 
    "rssi": 187, 
    "date": 1486088851000.0, 
    "filtered": 130192, 
    "type": "sgv", 
    "glucose": 111
  }, 
  {
    "trend_arrow": "45_DOWN", 
    "display_time": "2017-02-02T18:22:31-08:00", 
    "noise": 1, 
    "direction": "FortyFiveDown", 
    "system_time": "2017-02-03T02:21:44-08:00", 
    "sgv": 120, 
    "dateString": "2017-02-02T18:22:31-08:00", 
    "device": "openaps://indy-e1/cgm", 
    "unfiltered": 126832, 
    "rssi": 446, 
    "date": 1486088551000.0, 
    "filtered": 137248, 
    "type": "sgv", 
    "glucose": 120
  }, 
  {
    "trend_arrow": "45_DOWN", 
    "display_time": "2017-02-02T18:17:31-08:00", 
    "noise": 1, 
    "direction": "FortyFiveDown", 
    "system_time": "2017-02-03T02:16:43-08:00", 
    "sgv": 129, 
    "dateString": "2017-02-02T18:17:31-08:00", 
    "device": "openaps://indy-e1/cgm", 
    "unfiltered": 134144, 
    "rssi": 195, 
    "date": 1486088251000.0, 
    "filtered": 144544, 
    "type": "sgv", 
    "glucose": 129
  }
]